insightvault/__init__.py
insightvault/constants.py
insightvault/app/__init__.py
insightvault/app/base.py
insightvault/app/cli.py
insightvault/app/rag.py
insightvault/app/search.py
insightvault/app/summarizer.py
insightvault/models/__init__.py
insightvault/models/config.py
insightvault/models/database.py
insightvault/models/document.py
insightvault/services/__init__.py
insightvault/services/database.py
insightvault/services/embedding.py
insightvault/services/llm.py
insightvault/services/prompt.py
insightvault/services/splitter.py
insightvault/utils/logging.py
insightvault-0.0.3.dist-info/METADATA
insightvault-0.0.3.dist-info/WHEEL
insightvault-0.0.3.dist-info/entry_points.txt
insightvault-0.0.3.dist-info/licenses/LICENSE
insightvault-0.0.3.dist-info/RECORD
