Metadata-Version: 2.4
Name: insightvault
Version: 0.0.3
Summary: Local RAG pipeline runner
Author: David Kirchhoff
License: MIT License
License-File: LICENSE
Requires-Python: >=3.9
Requires-Dist: chromadb>=0.4.22
Requires-Dist: click>=8.1.7
Requires-Dist: fastapi>=0.109.2
Requires-Dist: llama-index>=0.12.5
Requires-Dist: ollama>=0.4.4
Requires-Dist: pydantic>=2.10.4
Requires-Dist: python-multipart>=0.0.9
Requires-Dist: sentence-transformers>=2.5.1
Requires-Dist: uvicorn>=0.27.1
Provides-Extra: dev
Requires-Dist: mypy>=1.8.0; extra == 'dev'
Requires-Dist: pre-commit>=4.0.1; extra == 'dev'
Requires-Dist: pytest-asyncio>=0.23.5; extra == 'dev'
Requires-Dist: pytest>=8.0.0; extra == 'dev'
Requires-Dist: ruff>=0.2.1; extra == 'dev'
Requires-Dist: twine>=6.0.1; extra == 'dev'
Requires-Dist: types-pyyaml>=6.0.12; extra == 'dev'
